{"cameraMode":{"drawMode":0,"name":"Shaded","section":"Shading Mode"},"sceneLighting":true,"audioPlay":false,"sceneViewState":{"m_AlwaysRefresh":false,"showFog":true,"showSkybox":true,"showFlares":true,"showImageEffects":true,"showParticleSystems":true,"showVisualEffectGraphs":true,"m_FxEnabled":true},"in2DMode":false,"pivot":{"x":-0.13283100724220277,"y":2.7123560905456545,"z":4.3285675048828129},"rotation":{"x":0.40676286816596987,"y":-0.0034363544546067716,"z":0.002104569226503372,"w":0.913792073726654},"size":10.203600883483887,"orthographic":false}